ss13_tools/__init__.py
ss13_tools/__main__.py
ss13_tools/__version__.py
ss13_tools/auth/__init__.py
ss13_tools/auth/__main__.py
ss13_tools/auth/constants.py
ss13_tools/auth/tg.py
ss13_tools/byond/__init__.py
ss13_tools/byond/__main__.py
ss13_tools/byond/constants.py
ss13_tools/byond/key_tools.py
ss13_tools/centcom/__init__.py
ss13_tools/centcom/__main__.py
ss13_tools/centcom/ban.py
ss13_tools/centcom/ban_types.py
ss13_tools/centcom/constants.py
ss13_tools/cli.py
ss13_tools/constants.py
ss13_tools/log_buddy/README.md
ss13_tools/log_buddy/__init__.py
ss13_tools/log_buddy/__main__.py
ss13_tools/log_buddy/constants.py
ss13_tools/log_buddy/expressions.py
ss13_tools/log_buddy/log.py
ss13_tools/log_buddy/log_magics.py
ss13_tools/log_buddy/log_parser.py
ss13_tools/log_downloader/__init__.py
ss13_tools/log_downloader/__main__.py
ss13_tools/log_downloader/base.py
ss13_tools/log_downloader/ckey.py
ss13_tools/log_downloader/constants.py
ss13_tools/log_downloader/round.py
ss13_tools/menu.py
ss13_tools/menu_item.py
ss13_tools/scrubby/CKeyController.py
ss13_tools/scrubby/RoundController.py
ss13_tools/scrubby/__init__.py
ss13_tools/scrubby/__main__.py
ss13_tools/scrubby/constants.py
ss13_tools/scrubby/investigate.py
ss13_tools/scrubby/round_data.py
ss13_tools/slur_detector/__init__.py
ss13_tools/slur_detector/__main__.py
ss13_tools/slur_detector/constants.py
ss13_tools/slur_detector/slur_detector.py
ss13_tools/slur_detector/slur_file.py
ss13_tools/slur_detector/word_detection.py
ss13_tools/util.py
ss13_tools-2.4.1.dist-info/LICENCE
ss13_tools-2.4.1.dist-info/METADATA
ss13_tools-2.4.1.dist-info/WHEEL
ss13_tools-2.4.1.dist-info/entry_points.txt
ss13_tools-2.4.1.dist-info/RECORD
