Metadata-Version: 2.1
Name: SS13-tools
Version: 2.4.1
Summary: Python toolchain for SS13
Home-page: https://github.com/RigglePrime/SS13-tools
Keywords: ss13,tgstation
Author: RigglePrime
Author-email: 27156122+RigglePrime@users.noreply.github.com
Requires-Python: >=3.8.10,<3.13
Classifier: Programming Language :: Python :: 3
Classifier: Programming Language :: Python :: 3.9
Classifier: Programming Language :: Python :: 3.10
Classifier: Programming Language :: Python :: 3.11
Classifier: Programming Language :: Python :: 3.12
Requires-Dist: aiohttp (>=3.8.3,<4.0.0)
Requires-Dist: colorama (>=0.4.6,<0.5.0)
Requires-Dist: ipython (>=8.12.0,<9.0.0)
Requires-Dist: pycryptodome (>=3.17,<4.0)
Requires-Dist: pyperclip (>=1.8.2,<2.0.0)
Requires-Dist: python-dateutil (>=2.8.2,<3.0.0)
Requires-Dist: requests (>=2.28.1,<3.0.0)
Requires-Dist: tqdm (>=4.64.1,<5.0.0)
Project-URL: Repository, https://github.com/RigglePrime/SS13-tools
